xarrayaita/__init__.py
xarrayaita/aita.py
xarrayaita/aita_export.py
xarrayaita/aita_geom.py
xarrayaita/aita_interactive_nb.py
xarrayaita/aita_plot.py
xarrayaita/aita_processing.py
xarrayaita/loadData_aita.py
xarrayaita-0.3.5.dist-info/LICENSE
xarrayaita-0.3.5.dist-info/METADATA
xarrayaita-0.3.5.dist-info/WHEEL
xarrayaita-0.3.5.dist-info/RECORD
