Metadata-Version: 2.3
Name: xarrayaita
Version: 0.3.5
Summary: Python librairy to process AITA data
Author: Thomas Chauve
Author-email: thomas.chauve@univ-grenoble-alpes.fr
Requires-Python: >=3.11,<4.0
Classifier: Programming Language :: Python :: 3
Classifier: Programming Language :: Python :: 3.11
Classifier: Programming Language :: Python :: 3.12
Classifier: Programming Language :: Python :: 3.13
Provides-Extra: docs
Requires-Dist: Sphinx ; extra == "docs"
Requires-Dist: ipympl
Requires-Dist: ipywidgets
Requires-Dist: jupyterlab
Requires-Dist: mahotas
Requires-Dist: matplotlib
Requires-Dist: nbsphinx ; extra == "docs"
Requires-Dist: nodejs
Requires-Dist: numpy
Requires-Dist: pandas
Requires-Dist: pandoc ; extra == "docs"
Requires-Dist: scikit-image
Requires-Dist: scipy
Requires-Dist: sphinx-rtd-theme ; extra == "docs"
Requires-Dist: tqdm
Requires-Dist: twine ; extra == "docs"
Requires-Dist: vtk
Requires-Dist: xarray
Requires-Dist: xarrayuvecs
